{
    "sourceFile": "src/i18n/en-US/introduction.ts",
    "activeCommit": 0,
    "commits": [
        {
            "activePatchIndex": 4,
            "patches": [
                {
                    "date": 1727240666686,
                    "content": "Index: \n===================================================================\n--- \n+++ \n"
                },
                {
                    "date": 1727240695827,
                    "content": "Index: \n===================================================================\n--- \n+++ \n@@ -1,5 +1,6 @@\n-{\n+const translation = {\n+    {\n     \"introduction.welcome\": \"Welcome to the GraphRAG Visualizer\",\n     \"introduction.overview\": \"Overview\",\n     \"introduction.overviewDescription\": \"This application visualizes Microsoft\",\n     \"introduction.overviewDescription2\": \"artifacts. Simply upload the parquet files to visualize the data without needing additional software like Gephi, Neo4j, or Jupyter Notebook.\",\n"
                },
                {
                    "date": 1727240734604,
                    "content": "Index: \n===================================================================\n--- \n+++ \n@@ -0,0 +1,38 @@\n+const translation = {\n+    \"welcome\": \"Welcome to the GraphRAG Visualizer\",\n+    \"overview\": \"Overview\",\n+    \"overviewDescription\": \"This application visualizes Microsoft\",\n+    \"overviewDescription2\": \"artifacts. Simply upload the parquet files to visualize the data without needing additional software like Gephi, Neo4j, or Jupyter Notebook.\",\n+    \"demoImageAlt\": \"Demo\",\n+    \"features\": \"Features\",\n+    \"feature1Title\": \"Graph Visualization:\",\n+    \"feature1Description\": \"View the graph in 2D or 3D in the \\\"Graph Visualization\\\" tab.\",\n+    \"feature2Title\": \"Data Tables:\",\n+    \"feature2Description\": \"Display data from the parquet files in the \\\"Data Tables\\\" tab.\",\n+    \"feature3Title\": \"Search Functionality:\",\n+    \"feature3Description\": \"Fully supports search, allowing users to focus on specific nodes or relationships.\",\n+    \"feature4Title\": \"Local Processing:\",\n+    \"feature4Description\": \"Your artifacts are processed locally on your machine. They are not uploaded anywhere, ensuring your data remains secure and private.\",\n+    \"usingSearchFunctionality\": \"Using the Search Functionality\",\n+    \"searchDescription1\": \"Once the\",\n+    \"searchDescription2\": \"server is up and running, you can perform searches directly through the GraphRAG Visualizer. This allows you to easily search and explore data that is hosted on your local server.\",\n+    \"searchImageAlt\": \"Search\",\n+    \"graphDataModel\": \"Graph Data Model\",\n+    \"graphDataModelDescription\": \"The logic for creating relationships for text units, documents, communities, and covariates is derived from the\",\n+    \"graphDataModelLinkText\": \"GraphRAG import Neo4j Cypher notebook\",\n+    \"nodes\": \"Nodes\",\n+    \"node\": \"Node\",\n+    \"type\": \"Type\",\n+    \"document\": \"Document\",\n+    \"textUnit\": \"Text Unit\",\n+    \"community\": \"Community\",\n+    \"finding\": \"Finding\",\n+    \"covariate\": \"Covariate\",\n+    \"entity\": \"Entity\",\n+    \"varies\": \"Varies\",\n+    \"relationships\": \"Relationships\",\n+    \"sourceNode\": \"Source Node\",\n+    \"relationship\": \"Relationship\",\n+    \"targetNode\": \"Target Node\"\n+  }\n+  \n\\ No newline at end of file\n"
                },
                {
                    "date": 1727240801343,
                    "content": "Index: \n===================================================================\n--- \n+++ \n@@ -34,44 +34,6 @@\n     \"sourceNode\": \"Source Node\",\n     \"relationship\": \"Relationship\",\n     \"targetNode\": \"Target Node\"\n   }\n-  \n-const translation = {\n-    {\n-    \"introduction.welcome\": \"Welcome to the GraphRAG Visualizer\",\n-    \"introduction.overview\": \"Overview\",\n-    \"introduction.overviewDescription\": \"This application visualizes Microsoft\",\n-    \"introduction.overviewDescription2\": \"artifacts. Simply upload the parquet files to visualize the data without needing additional software like Gephi, Neo4j, or Jupyter Notebook.\",\n-    \"introduction.demoImageAlt\": \"Demo\",\n-    \"introduction.features\": \"Features\",\n-    \"introduction.feature1Title\": \"Graph Visualization:\",\n-    \"introduction.feature1Description\": \"View the graph in 2D or 3D in the \\\"Graph Visualization\\\" tab.\",\n-    \"introduction.feature2Title\": \"Data Tables:\",\n-    \"introduction.feature2Description\": \"Display data from the parquet files in the \\\"Data Tables\\\" tab.\",\n-    \"introduction.feature3Title\": \"Search Functionality:\",\n-    \"introduction.feature3Description\": \"Fully supports search, allowing users to focus on specific nodes or relationships.\",\n-    \"introduction.feature4Title\": \"Local Processing:\",\n-    \"introduction.feature4Description\": \"Your artifacts are processed locally on your machine. They are not uploaded anywhere, ensuring your data remains secure and private.\",\n-    \"introduction.usingSearchFunctionality\": \"Using the Search Functionality\",\n-    \"introduction.searchDescription1\": \"Once the\",\n-    \"introduction.searchDescription2\": \"server is up and running, you can perform searches directly through the GraphRAG Visualizer. This allows you to easily search and explore data that is hosted on your local server.\",\n-    \"introduction.searchImageAlt\": \"Search\",\n-    \"introduction.graphDataModel\": \"Graph Data Model\",\n-    \"introduction.graphDataModelDescription\": \"The logic for creating relationships for text units, documents, communities, and covariates is derived from the\",\n-    \"introduction.graphDataModelLinkText\": \"GraphRAG import Neo4j Cypher notebook\",\n-    \"introduction.nodes\": \"Nodes\",\n-    \"introduction.node\": \"Node\",\n-    \"introduction.type\": \"Type\",\n-    \"introduction.document\": \"Document\",\n-    \"introduction.textUnit\": \"Text Unit\",\n-    \"introduction.community\": \"Community\",\n-    \"introduction.finding\": \"Finding\",\n-    \"introduction.covariate\": \"Covariate\",\n-    \"introduction.entity\": \"Entity\",\n-    \"introduction.varies\": \"Varies\",\n-    \"introduction.relationships\": \"Relationships\",\n-    \"introduction.sourceNode\": \"Source Node\",\n-    \"introduction.relationship\": \"Relationship\",\n-    \"introduction.targetNode\": \"Target Node\"\n-  }\n-  \n\\ No newline at end of file\n+\n+export default translation\n"
                },
                {
                    "date": 1727240806892,
                    "content": "Index: \n===================================================================\n--- \n+++ \n@@ -33,7 +33,7 @@\n     \"relationships\": \"Relationships\",\n     \"sourceNode\": \"Source Node\",\n     \"relationship\": \"Relationship\",\n     \"targetNode\": \"Target Node\"\n-  }\n+}\n \n export default translation\n"
                }
            ],
            "date": 1727240666686,
            "name": "Commit-0",
            "content": "{\n    \"introduction.welcome\": \"Welcome to the GraphRAG Visualizer\",\n    \"introduction.overview\": \"Overview\",\n    \"introduction.overviewDescription\": \"This application visualizes Microsoft\",\n    \"introduction.overviewDescription2\": \"artifacts. Simply upload the parquet files to visualize the data without needing additional software like Gephi, Neo4j, or Jupyter Notebook.\",\n    \"introduction.demoImageAlt\": \"Demo\",\n    \"introduction.features\": \"Features\",\n    \"introduction.feature1Title\": \"Graph Visualization:\",\n    \"introduction.feature1Description\": \"View the graph in 2D or 3D in the \\\"Graph Visualization\\\" tab.\",\n    \"introduction.feature2Title\": \"Data Tables:\",\n    \"introduction.feature2Description\": \"Display data from the parquet files in the \\\"Data Tables\\\" tab.\",\n    \"introduction.feature3Title\": \"Search Functionality:\",\n    \"introduction.feature3Description\": \"Fully supports search, allowing users to focus on specific nodes or relationships.\",\n    \"introduction.feature4Title\": \"Local Processing:\",\n    \"introduction.feature4Description\": \"Your artifacts are processed locally on your machine. They are not uploaded anywhere, ensuring your data remains secure and private.\",\n    \"introduction.usingSearchFunctionality\": \"Using the Search Functionality\",\n    \"introduction.searchDescription1\": \"Once the\",\n    \"introduction.searchDescription2\": \"server is up and running, you can perform searches directly through the GraphRAG Visualizer. This allows you to easily search and explore data that is hosted on your local server.\",\n    \"introduction.searchImageAlt\": \"Search\",\n    \"introduction.graphDataModel\": \"Graph Data Model\",\n    \"introduction.graphDataModelDescription\": \"The logic for creating relationships for text units, documents, communities, and covariates is derived from the\",\n    \"introduction.graphDataModelLinkText\": \"GraphRAG import Neo4j Cypher notebook\",\n    \"introduction.nodes\": \"Nodes\",\n    \"introduction.node\": \"Node\",\n    \"introduction.type\": \"Type\",\n    \"introduction.document\": \"Document\",\n    \"introduction.textUnit\": \"Text Unit\",\n    \"introduction.community\": \"Community\",\n    \"introduction.finding\": \"Finding\",\n    \"introduction.covariate\": \"Covariate\",\n    \"introduction.entity\": \"Entity\",\n    \"introduction.varies\": \"Varies\",\n    \"introduction.relationships\": \"Relationships\",\n    \"introduction.sourceNode\": \"Source Node\",\n    \"introduction.relationship\": \"Relationship\",\n    \"introduction.targetNode\": \"Target Node\"\n  }\n  "
        }
    ]
}