{
    "sourceFile": "src/i18n/zh-Hans/introduction.ts",
    "activeCommit": 0,
    "commits": [
        {
            "activePatchIndex": 4,
            "patches": [
                {
                    "date": 1727240676388,
                    "content": "Index: \n===================================================================\n--- \n+++ \n"
                },
                {
                    "date": 1727240751697,
                    "content": "Index: \n===================================================================\n--- \n+++ \n@@ -1,5 +1,6 @@\n-{\n+const translation = {\n+    {\n     \"introduction.welcome\": \"欢迎使用 GraphRAG 可视化工具\",\n     \"introduction.overview\": \"概述\",\n     \"introduction.overviewDescription\": \"该应用程序可视化微软\",\n     \"introduction.overviewDescription2\": \"的成果。只需上传 parquet 文件即可可视化数据，无需额外的软件，如 Gephi、Neo4j 或 Jupyter Notebook。\",\n"
                },
                {
                    "date": 1727240756717,
                    "content": "Index: \n===================================================================\n--- \n+++ \n@@ -1,39 +1,38 @@\n const translation = {\n-    {\n-    \"introduction.welcome\": \"欢迎使用 GraphRAG 可视化工具\",\n-    \"introduction.overview\": \"概述\",\n-    \"introduction.overviewDescription\": \"该应用程序可视化微软\",\n-    \"introduction.overviewDescription2\": \"的成果。只需上传 parquet 文件即可可视化数据，无需额外的软件，如 Gephi、Neo4j 或 Jupyter Notebook。\",\n-    \"introduction.demoImageAlt\": \"演示\",\n-    \"introduction.features\": \"功能\",\n-    \"introduction.feature1Title\": \"图形可视化：\",\n-    \"introduction.feature1Description\": \"在“图形可视化”选项卡中以 2D 或 3D 查看图形。\",\n-    \"introduction.feature2Title\": \"数据表：\",\n-    \"introduction.feature2Description\": \"在“数据表”选项卡中显示 parquet 文件中的数据。\",\n-    \"introduction.feature3Title\": \"搜索功能：\",\n-    \"introduction.feature3Description\": \"完全支持搜索，允许用户专注于特定的节点或关系。\",\n-    \"introduction.feature4Title\": \"本地处理：\",\n-    \"introduction.feature4Description\": \"您的文件将在本地机器上处理，不会上传到任何地方，确保您的数据安全和私密。\",\n-    \"introduction.usingSearchFunctionality\": \"使用搜索功能\",\n-    \"introduction.searchDescription1\": \"一旦\",\n-    \"introduction.searchDescription2\": \"服务器启动并运行，您可以直接通过 GraphRAG 可视化工具执行搜索。这使您可以轻松搜索和探索托管在本地服务器上的数据。\",\n-    \"introduction.searchImageAlt\": \"搜索\",\n-    \"introduction.graphDataModel\": \"图形数据模型\",\n-    \"introduction.graphDataModelDescription\": \"创建文本单元、文档、社区和协变量的关系逻辑来自\",\n-    \"introduction.graphDataModelLinkText\": \"GraphRAG 导入 Neo4j Cypher 笔记本\",\n-    \"introduction.nodes\": \"节点\",\n-    \"introduction.node\": \"节点\",\n-    \"introduction.type\": \"类型\",\n-    \"introduction.document\": \"文档\",\n-    \"introduction.textUnit\": \"文本单元\",\n-    \"introduction.community\": \"社区\",\n-    \"introduction.finding\": \"发现\",\n-    \"introduction.covariate\": \"协变量\",\n-    \"introduction.entity\": \"实体\",\n-    \"introduction.varies\": \"多种\",\n-    \"introduction.relationships\": \"关系\",\n-    \"introduction.sourceNode\": \"源节点\",\n-    \"introduction.relationship\": \"关系\",\n-    \"introduction.targetNode\": \"目标节点\"\n+    \"welcome\": \"欢迎使用 GraphRAG 可视化工具\",\n+    \"overview\": \"概述\",\n+    \"overviewDescription\": \"该应用程序可视化微软\",\n+    \"overviewDescription2\": \"的成果。只需上传 parquet 文件即可可视化数据，无需额外的软件，如 Gephi、Neo4j 或 Jupyter Notebook。\",\n+    \"demoImageAlt\": \"演示\",\n+    \"features\": \"功能\",\n+    \"feature1Title\": \"图形可视化：\",\n+    \"feature1Description\": \"在“图形可视化”选项卡中以 2D 或 3D 查看图形。\",\n+    \"feature2Title\": \"数据表：\",\n+    \"feature2Description\": \"在“数据表”选项卡中显示 parquet 文件中的数据。\",\n+    \"feature3Title\": \"搜索功能：\",\n+    \"feature3Description\": \"完全支持搜索，允许用户专注于特定的节点或关系。\",\n+    \"feature4Title\": \"本地处理：\",\n+    \"feature4Description\": \"您的文件将在本地机器上处理，不会上传到任何地方，确保您的数据安全和私密。\",\n+    \"usingSearchFunctionality\": \"使用搜索功能\",\n+    \"searchDescription1\": \"一旦\",\n+    \"searchDescription2\": \"服务器启动并运行，您可以直接通过 GraphRAG 可视化工具执行搜索。这使您可以轻松搜索和探索托管在本地服务器上的数据。\",\n+    \"searchImageAlt\": \"搜索\",\n+    \"graphDataModel\": \"图形数据模型\",\n+    \"graphDataModelDescription\": \"创建文本单元、文档、社区和协变量的关系逻辑来自\",\n+    \"graphDataModelLinkText\": \"GraphRAG 导入 Neo4j Cypher 笔记本\",\n+    \"nodes\": \"节点\",\n+    \"node\": \"节点\",\n+    \"type\": \"类型\",\n+    \"document\": \"文档\",\n+    \"textUnit\": \"文本单元\",\n+    \"community\": \"社区\",\n+    \"finding\": \"发现\",\n+    \"covariate\": \"协变量\",\n+    \"entity\": \"实体\",\n+    \"varies\": \"多种\",\n+    \"relationships\": \"关系\",\n+    \"sourceNode\": \"源节点\",\n+    \"relationship\": \"关系\",\n+    \"targetNode\": \"目标节点\"\n   }\n   \n\\ No newline at end of file\n"
                },
                {
                    "date": 1727240782603,
                    "content": "Index: \n===================================================================\n--- \n+++ \n@@ -34,5 +34,6 @@\n     \"sourceNode\": \"源节点\",\n     \"relationship\": \"关系\",\n     \"targetNode\": \"目标节点\"\n   }\n+  \n   \n\\ No newline at end of file\n"
                },
                {
                    "date": 1727240787768,
                    "content": "Index: \n===================================================================\n--- \n+++ \n@@ -33,7 +33,7 @@\n     \"relationships\": \"关系\",\n     \"sourceNode\": \"源节点\",\n     \"relationship\": \"关系\",\n     \"targetNode\": \"目标节点\"\n-  }\n+}\n   \n\\ No newline at end of file\n-  \n+export default translation\n"
                }
            ],
            "date": 1727240676388,
            "name": "Commit-0",
            "content": "{\n    \"introduction.welcome\": \"欢迎使用 GraphRAG 可视化工具\",\n    \"introduction.overview\": \"概述\",\n    \"introduction.overviewDescription\": \"该应用程序可视化微软\",\n    \"introduction.overviewDescription2\": \"的成果。只需上传 parquet 文件即可可视化数据，无需额外的软件，如 Gephi、Neo4j 或 Jupyter Notebook。\",\n    \"introduction.demoImageAlt\": \"演示\",\n    \"introduction.features\": \"功能\",\n    \"introduction.feature1Title\": \"图形可视化：\",\n    \"introduction.feature1Description\": \"在“图形可视化”选项卡中以 2D 或 3D 查看图形。\",\n    \"introduction.feature2Title\": \"数据表：\",\n    \"introduction.feature2Description\": \"在“数据表”选项卡中显示 parquet 文件中的数据。\",\n    \"introduction.feature3Title\": \"搜索功能：\",\n    \"introduction.feature3Description\": \"完全支持搜索，允许用户专注于特定的节点或关系。\",\n    \"introduction.feature4Title\": \"本地处理：\",\n    \"introduction.feature4Description\": \"您的文件将在本地机器上处理，不会上传到任何地方，确保您的数据安全和私密。\",\n    \"introduction.usingSearchFunctionality\": \"使用搜索功能\",\n    \"introduction.searchDescription1\": \"一旦\",\n    \"introduction.searchDescription2\": \"服务器启动并运行，您可以直接通过 GraphRAG 可视化工具执行搜索。这使您可以轻松搜索和探索托管在本地服务器上的数据。\",\n    \"introduction.searchImageAlt\": \"搜索\",\n    \"introduction.graphDataModel\": \"图形数据模型\",\n    \"introduction.graphDataModelDescription\": \"创建文本单元、文档、社区和协变量的关系逻辑来自\",\n    \"introduction.graphDataModelLinkText\": \"GraphRAG 导入 Neo4j Cypher 笔记本\",\n    \"introduction.nodes\": \"节点\",\n    \"introduction.node\": \"节点\",\n    \"introduction.type\": \"类型\",\n    \"introduction.document\": \"文档\",\n    \"introduction.textUnit\": \"文本单元\",\n    \"introduction.community\": \"社区\",\n    \"introduction.finding\": \"发现\",\n    \"introduction.covariate\": \"协变量\",\n    \"introduction.entity\": \"实体\",\n    \"introduction.varies\": \"多种\",\n    \"introduction.relationships\": \"关系\",\n    \"introduction.sourceNode\": \"源节点\",\n    \"introduction.relationship\": \"关系\",\n    \"introduction.targetNode\": \"目标节点\"\n  }\n  "
        }
    ]
}